yta_web_resources/__init__.py
yta_web_resources/web/__init__.py
yta_web_resources/web/booking/__init__.py
yta_web_resources/web/booking/index.html
yta_web_resources/web/discord/__init__.py
yta_web_resources/web/discord/index.html
yta_web_resources/web/iphone/__init__.py
yta_web_resources/web/iphone/index.html
yta_web_resources-0.0.6.dist-info/licenses/LICENSE
yta_web_resources-0.0.6.dist-info/METADATA
yta_web_resources-0.0.6.dist-info/WHEEL
yta_web_resources-0.0.6.dist-info/RECORD
