Metadata-Version: 2.4
Name: yta-web-resources
Version: 0.0.6
Summary: Youtube Autonomous Web Resources module
License-File: LICENSE
Author: danialcala94
Author-email: danielalcalavalera@gmail.com
Requires-Python: ==3.9
Classifier: Programming Language :: Python :: 3
Classifier: Programming Language :: Python :: 3.9
Requires-Dist: yta_file (>=0.0.1,<1.0.0)
Requires-Dist: yta_file_downloader (>=0.0.1,<1.0.0)
Requires-Dist: yta_google_drive_downloader (>=0.0.1,<1.0.0)
Requires-Dist: yta_programming_path (>=0.0.1,<1.0.0)
Requires-Dist: yta_web_scraper (>=0.0.1,<1.0.0)
